[{"category_id":1, "name":"Spectroscopy", "external_schema_uri":"", "item_count_internal":16, "item_count_public":16},
 {"category_id":2, "name":"X-ray Analysis", "external_schema_uri":"", "item_count_internal":5, "item_count_public":3},
 {"category_id":3, "name":"Chromatography", "external_schema_uri":"", "item_count_internal":12, "item_count_public":12},
 {"category_id":4, "name":"Optical Microscopy", "external_schema_uri":"", "item_count_internal":17, "item_count_public":17},
 {"category_id":5, "name":"Chemical Analysis", "external_schema_uri":"", "item_count_internal":28, "item_count_public":28},
 {"category_id":6, "name":"Laser Devices", "external_schema_uri":"", "item_count_internal":6, "item_count_public":6},
 {"category_id":7, "name":"Computation", "external_schema_uri":"", "item_count_internal":3, "item_count_public":3},
 {"category_id":8, "name":"Ovens", "external_schema_uri":"", "item_count_internal":6, "item_count_public":6},
 {"category_id":9, "name":"Sample Preparation/Analysis", "external_schema_uri":"", "item_count_internal":21, "item_count_public":21},
 {"category_id":10, "name":"Controllers", "external_schema_uri":"", "item_count_internal":6, "item_count_public":6},
 {"category_id":11, "name":"Physical Properties Measurement", "external_schema_uri":"", "item_count_internal":2, "item_count_public":2},
 {"category_id":12, "name":"Biotechnology", "external_schema_uri":"", "item_count_internal":13, "item_count_public":13},
 {"category_id":13, "name":"Geology", "external_schema_uri":"", "item_count_internal":17, "item_count_public":17},
 {"category_id":14, "name":"Water Analysis", "external_schema_uri":"", "item_count_internal":2, "item_count_public":2}]